setup.py
aperture/__init__.py
aperture/heatmaps.py
aperture/set_plot_params.py
aperture/solarized.py
aperture/util.py
aperture.egg-info/PKG-INFO
aperture.egg-info/SOURCES.txt
aperture.egg-info/dependency_links.txt
aperture.egg-info/not-zip-safe
aperture.egg-info/requires.txt
aperture.egg-info/top_level.txt