Metadata-Version: 1.0
Name: aperture
Version: 0.1.14
Summary: Wrappers, settings, and extensions for Python/matplotlib
Home-page: https://github.com/kevinsprong23/aperture
Author: Kevin Sprong
Author-email: kevin@kevinsprong.com
License: MIT
Platform: UNKNOWN
